ml/__init__.py
ml/train.py
ml/architectures/__init__.py
ml/architectures/efficientnet.py
ml/datautils/__init__.py
ml/datautils/dataset_generator.py
quantum/__init__.py
AutoQAI-0.0.4.dist-info/LICENSE
AutoQAI-0.0.4.dist-info/METADATA
AutoQAI-0.0.4.dist-info/WHEEL
AutoQAI-0.0.4.dist-info/top_level.txt
AutoQAI-0.0.4.dist-info/RECORD
